dysys/__init__.py
dysys/controltf.py
dysys/statespacesymbolic.py
dysys/sysdyn.py
dysys/transferfunctions.py
dysys/transferfunctionsymbolic.py
dysys-0.1.8.dist-info/LICENSE
dysys-0.1.8.dist-info/METADATA
dysys-0.1.8.dist-info/WHEEL
dysys-0.1.8.dist-info/RECORD
