Metadata-Version: 2.1
Name: dysys
Version: 0.1.8
Summary: A package for working with system dynamics symbolically and numerically
License: MIT
Author: Rico Picone
Author-email: rpicone@stmartin.edu
Requires-Python: >=3.11,<4.0
Classifier: License :: OSI Approved :: MIT License
Classifier: Programming Language :: Python :: 3
Classifier: Programming Language :: Python :: 3.11
Requires-Dist: control (>=0.9.4,<0.10.0)
Requires-Dist: engcom (>=0.1.20,<0.2.0)
Requires-Dist: matplotlib (>=3.8.3,<4.0.0)
Requires-Dist: numpy (>=1.26.4,<2.0.0)
Requires-Dist: scipy (>=1.12.0,<2.0.0)
Requires-Dist: sympy (>=1.12,<2.0)
